{
    "@class": "com.kony.gen.viz.model.component.KVizImage2",
    "DNDConfig": null,
    "__parentReadjusting__": false,
    "_base64_": null,
    "_height_": {
        "type": "string",
        "value": "90dp"
    },
    "_left_": {
        "type": "string",
        "value": "139dp"
    },
    "_margin_": [
        0,
        0,
        0,
        0
    ],
    "_padding_": [
        0,
        0,
        0,
        0
    ],
    "_skin_": "sd53fdbb6ac348c7a5ad64cf54bd7058",
    "_src_": "https://yoshikiito.net/blog/wp-content/uploads/2016/09/electorn-logo.png",
    "_top_": {
        "type": "string",
        "value": "10%"
    },
    "_width_": {
        "type": "string",
        "value": "83dp"
    },
    "canUpdateUI": true,
    "containerweight": 100,
    "context": {
        "channel": "mobile",
        "formID": "Form1",
        "platform": "android",
        "templateType": "forms",
        "topLevelBox": null
    },
    "id": "userLogo",
    "imagescalemode": 1,
    "info": null,
    "invokedProperty": "src",
    "iscustomlayout": false,
    "isvisible": true,
    "kuid": "b170fdd049c54fa28590925e4343a093",
    "name": "kony.ui.Image2",
    "parent": "Form1",
    "pf": "Form1",
    "retaincontentalignment": false,
    "retainflexpositionproperties": false,
    "srcType": 1,
    "wType": "Image",
    "widgetalignment": 5,
    "zindex": 1
}